doris/LICENSE.TXT
doris/README.TXT
doris/__init__.py
doris/__main__.py
doris/config.py
doris/dialog.py
doris/doris.py
doris/doris.ui
doris/doris_functions.py
doris/doris_qrc.py
doris/doris_ui.py
doris/version.py
doris/icons/doris_logo.128px.png
doris/icons/doris_logo.256px.png
doris/icons/doris_logo.ico
doris_tracker-2022.12.20.dist-info/LICENSE.TXT
doris_tracker-2022.12.20.dist-info/METADATA
doris_tracker-2022.12.20.dist-info/WHEEL
doris_tracker-2022.12.20.dist-info/entry_points.txt
doris_tracker-2022.12.20.dist-info/top_level.txt
doris_tracker-2022.12.20.dist-info/RECORD
