Metadata-Version: 2.1
Name: doris-tracker
Version: 2022.12.20
Summary: DORIS
Home-page: http://www.boris.unito.it/pages/doris
Author: Olivier Friard
Author-email: olivier.friard@unito.it
Classifier: Intended Audience :: Science/Research
Classifier: Intended Audience :: Education
Classifier: Programming Language :: Python :: 3.8
Classifier: Programming Language :: Python :: 3.8
Classifier: Programming Language :: Python :: 3.9
Classifier: Programming Language :: Python :: 3.10
Classifier: License :: OSI Approved :: GNU General Public License v3 (GPLv3)
Classifier: Operating System :: OS Independent
Classifier: Topic :: Scientific/Engineering
Requires-Python: >=3.8
License-File: LICENSE.TXT
Requires-Dist: matplotlib
Requires-Dist: numpy
Requires-Dist: opencv-python-headless
Requires-Dist: pandas
Requires-Dist: pyqt5
Requires-Dist: scikit-learn
Requires-Dist: scipy
Requires-Dist: sklearn
